{
  "kind": "collectionType",
  "collectionName": "home_pages",
  "info": {
    "singularName": "home-page",
    "pluralName": "home-pages",
    "displayName": "homePages",
    "description": ""
  },
  "options": {
    "draftAndPublish": true
  },
  "pluginOptions": {},
  "attributes": {
    "backgroundImage": {
      "type": "media",
      "multiple": false,
      "required": false,
      "allowedTypes": [
        "images",
        "files",
        "videos",
        "audios"
      ]
    },
    "showFormButton": {
      "type": "boolean",
      "default": true
    }
  }
}
